odoo10_addon_website_multi_theme-10.0.1.4.0-py2.7-nspkg.pth
odoo/addons/website_multi_theme/README.rst
odoo/addons/website_multi_theme/__init__.py
odoo/addons/website_multi_theme/__manifest__.py
odoo/addons/website_multi_theme/controllers/__init__.py
odoo/addons/website_multi_theme/controllers/main.py
odoo/addons/website_multi_theme/data/themes_bootswatch.xml
odoo/addons/website_multi_theme/data/themes_default.xml
odoo/addons/website_multi_theme/data/themes_private.xml
odoo/addons/website_multi_theme/demo/pages.xml
odoo/addons/website_multi_theme/demo/themes.xml
odoo/addons/website_multi_theme/migrations/10.0.1.1.0/pre-migrate.py
odoo/addons/website_multi_theme/migrations/10.0.1.2.0/post-multi_theme_generated.py
odoo/addons/website_multi_theme/migrations/10.0.1.2.0/pre-multi_theme_generated.py
odoo/addons/website_multi_theme/models/__init__.py
odoo/addons/website_multi_theme/models/ir_model_data.py
odoo/addons/website_multi_theme/models/ir_qweb.py
odoo/addons/website_multi_theme/models/ir_ui_view.py
odoo/addons/website_multi_theme/models/website.py
odoo/addons/website_multi_theme/models/website_theme.py
odoo/addons/website_multi_theme/security/ir.model.access.csv
odoo/addons/website_multi_theme/static/description/icon.png
odoo/addons/website_multi_theme/static/src/css/demo.less
odoo/addons/website_multi_theme/static/src/img/snippets/s_demo.png
odoo/addons/website_multi_theme/static/src/js/theme.js
odoo/addons/website_multi_theme/templates/assets.xml
odoo/addons/website_multi_theme/templates/patterns.xml
odoo/addons/website_multi_theme/tests/__init__.py
odoo/addons/website_multi_theme/tests/test_assets.py
odoo/addons/website_multi_theme/tests/test_themes.py
odoo/addons/website_multi_theme/tests/test_website_editor.py
odoo/addons/website_multi_theme/views/ir_ui_view.xml
odoo/addons/website_multi_theme/wizards/__init__.py
odoo/addons/website_multi_theme/wizards/website_config_settings.py
odoo10_addon_website_multi_theme-10.0.1.4.0.dist-info/DESCRIPTION.rst
odoo10_addon_website_multi_theme-10.0.1.4.0.dist-info/METADATA
odoo10_addon_website_multi_theme-10.0.1.4.0.dist-info/RECORD
odoo10_addon_website_multi_theme-10.0.1.4.0.dist-info/WHEEL
odoo10_addon_website_multi_theme-10.0.1.4.0.dist-info/metadata.json
odoo10_addon_website_multi_theme-10.0.1.4.0.dist-info/namespace_packages.txt
odoo10_addon_website_multi_theme-10.0.1.4.0.dist-info/top_level.txt
